k8s_metrix/__init__.py
k8s_metrix/main.py
k8s_metrix-0.1.0.dist-info/LICENSE
k8s_metrix-0.1.0.dist-info/METADATA
k8s_metrix-0.1.0.dist-info/WHEEL
k8s_metrix-0.1.0.dist-info/RECORD
